burdock/cli/__init__.py
burdock/cli/__main__.py
burdock/core/__init__.py
burdock/core/burdock.py
burdock/core/type.py
burdock/core/variable.py
burdock/core/templates/decls.jinja2
burdock/core/templates/dtrace.jinja2
burdock/expander/__init__.py
burdock/expander/base.py
burdock/expander/common.py
burdock/matcher/__init__.py
burdock/matcher/base.py
burdock/matcher/common.py
burdock/util/__init__.py
burdock/util/contracts.py
burdock/util/subprocess.py
burdock-0.1.2.dist-info/LICENSE
burdock-0.1.2.dist-info/METADATA
burdock-0.1.2.dist-info/WHEEL
burdock-0.1.2.dist-info/entry_points.txt
burdock-0.1.2.dist-info/top_level.txt
burdock-0.1.2.dist-info/RECORD
