Metadata-Version: 2.1
Name: burdock
Version: 0.1.2
Summary: A Daikon frontend for Python data frames and CSV/TSV files.
Home-page: https://github.com/DylanLukes/burdock
Author: Dylan A. Lukes
Author-email: dlukes@eng.ucsd.edu
License: BSD 3-Clause
Platform: UNKNOWN
Requires-Dist: pandas
Requires-Dist: jinja2
